movielite/__init__.py
movielite/bootstrap.py
movielite/enums.py
movielite/logger.py
movielite/afx/__init__.py
movielite/afx/base.py
movielite/afx/fade.py
movielite/audio/__init__.py
movielite/audio/audio_clip.py
movielite/composite/__init__.py
movielite/composite/alpha_composite_clip.py
movielite/composite/composite_clip.py
movielite/core/__init__.py
movielite/core/empty_frame.py
movielite/core/graphic_clip.py
movielite/core/media_clip.py
movielite/core/video_writer.py
movielite/image/__init__.py
movielite/image/image_clip.py
movielite/image/text_clip.py
movielite/vfx/__init__.py
movielite/vfx/base.py
movielite/vfx/blur.py
movielite/vfx/color.py
movielite/vfx/fade.py
movielite/vfx/glitch.py
movielite/vfx/rotation.py
movielite/vfx/vignette.py
movielite/vfx/zoom.py
movielite/video/__init__.py
movielite/video/alpha_video_clip.py
movielite/video/video_clip.py
movielite/vtx/__init__.py
movielite/vtx/base.py
movielite/vtx/blur_dissolve.py
movielite/vtx/crossfade.py
movielite/vtx/dissolve.py
movielite-0.2.2.dist-info/METADATA
movielite-0.2.2.dist-info/WHEEL
movielite-0.2.2.dist-info/licenses/LICENSE
movielite-0.2.2.dist-info/RECORD
