Metadata-Version: 2.4
Name: movielite
Version: 0.2.2
Summary: A performance-oriented Python video editing library focused on speed and simplicity.
Project-URL: Homepage, https://github.com/francozanardi/movielite
Project-URL: Repository, https://github.com/francozanardi/movielite
Project-URL: Bug Tracker, https://github.com/francozanardi/movielite/issues
Author-email: Franco Zanardi <francozanardi97@gmail.com>
License: MIT License
License-File: LICENSE
Keywords: ffmpeg,moviepy,performance,video,video editing,video processing
Classifier: Development Status :: 3 - Alpha
Classifier: Intended Audience :: Developers
Classifier: License :: OSI Approved :: MIT License
Classifier: Operating System :: OS Independent
Classifier: Programming Language :: Python :: 3
Classifier: Programming Language :: Python :: 3.10
Classifier: Programming Language :: Python :: 3.11
Classifier: Programming Language :: Python :: 3.12
Classifier: Topic :: Multimedia
Classifier: Topic :: Multimedia :: Sound/Audio
Classifier: Topic :: Multimedia :: Sound/Audio :: Analysis
Classifier: Topic :: Multimedia :: Video
Classifier: Topic :: Multimedia :: Video :: Capture
Classifier: Topic :: Multimedia :: Video :: Conversion
Requires-Python: >=3.10
Requires-Dist: multiprocess
Requires-Dist: numba
Requires-Dist: numpy
Requires-Dist: opencv-python
Requires-Dist: pictex
Requires-Dist: tqdm
Requires-Dist: typing-extensions>=4.0; python_version < '3.11'
Provides-Extra: test
Requires-Dist: pytest; extra == 'test'
Requires-Dist: pytest-cov; extra == 'test'
